MANIFEST.in
README.rst
VERSION
setup.py
commandlib/__init__.py
commandlib/command.py
commandlib/command_path.py
commandlib/deprecated.py
commandlib/exceptions.py
commandlib/piped.py
commandlib/utils.py
commandlib.egg-info/PKG-INFO
commandlib.egg-info/SOURCES.txt
commandlib.egg-info/dependency_links.txt
commandlib.egg-info/not-zip-safe
commandlib.egg-info/top_level.txt